instrumental/__about__.py
instrumental/__init__.py
instrumental/appdirs.py
instrumental/conf.py
instrumental/driver_info.py
instrumental/errors.py
instrumental/fitting.py
instrumental/gui.py
instrumental/instrumental.conf.default
instrumental/log.py
instrumental/parse_modules.py
instrumental/plotting.py
instrumental/std_modules.py
instrumental/tools.py
instrumental/util.py
instrumental/drivers/__init__.py
instrumental/drivers/decorator.py
instrumental/drivers/facet.py
instrumental/drivers/remote.py
instrumental/drivers/util.py
instrumental/drivers/cameras/__init__.py
instrumental/drivers/cameras/_build_picam.py
instrumental/drivers/cameras/_build_pixelfly.py
instrumental/drivers/cameras/_build_uc480.py
instrumental/drivers/cameras/pco.py
instrumental/drivers/cameras/picam.py
instrumental/drivers/cameras/pixelfly.py
instrumental/drivers/cameras/pvcam.py
instrumental/drivers/cameras/tsi.py
instrumental/drivers/cameras/uc480.py
instrumental/drivers/cameras/_pco/__init__.py
instrumental/drivers/cameras/_pco/clean.h
instrumental/drivers/cameras/_pixelfly/__init__.py
instrumental/drivers/cameras/_pvcam/__init__.py
instrumental/drivers/cameras/_pvcam/macros.py
instrumental/drivers/cameras/_pvcam/pvcam_clean.h
instrumental/drivers/cameras/_tsi/__init__.py
instrumental/drivers/cameras/_tsi/tsi.h
instrumental/drivers/daq/__init__.py
instrumental/drivers/daq/_build_ni.py
instrumental/drivers/daq/ni.py
instrumental/drivers/funcgenerators/__init__.py
instrumental/drivers/funcgenerators/agilent.py
instrumental/drivers/funcgenerators/rigol.py
instrumental/drivers/funcgenerators/tektronix.py
instrumental/drivers/laserdiodecontrollers/__init__.py
instrumental/drivers/laserdiodecontrollers/ilx_lightwave.py
instrumental/drivers/lasers/__init__.py
instrumental/drivers/lasers/femto_ferb.py
instrumental/drivers/lasers/santec.py
instrumental/drivers/lockins/__init__.py
instrumental/drivers/lockins/sr844.py
instrumental/drivers/lockins/sr850.py
instrumental/drivers/motion/__init__.py
Instrumental_lib-0.8.dist-info/LICENSE
Instrumental_lib-0.8.dist-info/METADATA
Instrumental_lib-0.8.dist-info/WHEEL
Instrumental_lib-0.8.dist-info/top_level.txt
Instrumental_lib-0.8.dist-info/RECORD
